bertdotbill/__init__.py
bertdotbill/app.py
bertdotbill/args.py
bertdotbill/config.py
bertdotbill/defaults.py
bertdotbill/entrypoint.py
bertdotbill/extensions.py
bertdotbill/lessons.py
bertdotbill/logger.py
bertdotbill/topics.py
bertdotbill/websocket.py
bertdotbill/webterminal.py
bertdotbill/spyder_terminal/__init__.py
bertdotbill/spyder_terminal/server/__init__.py
bertdotbill/spyder_terminal/server/common.py
bertdotbill/spyder_terminal/server/routes.py
bertdotbill/spyder_terminal/server/logic/__init__.py
bertdotbill/spyder_terminal/server/logic/term_manager.py
bertdotbill/spyder_terminal/server/rest/__init__.py
bertdotbill/spyder_terminal/server/rest/term_rest.py
bertdotbill/spyder_terminal/server/tests/__init__.py
bertdotbill/spyder_terminal/server/tests/print_size.py
bertdotbill/spyder_terminal/server/tests/test_server.py
bertdotbill/spyder_terminal/server/web/__init__.py
bertdotbill/spyder_terminal/server/web/main_handler.py
bertdotbill/spyder_terminal/server/websockets/__init__.py
bertdotbill/spyder_terminal/server/websockets/term_ws.py
bertdotbill-2.9.0.data/data/bin/bill.gui/bert.bill.2f0dc019.css
bertdotbill-2.9.0.data/data/bin/bill.gui/bert.bill.2f0dc019.css.br
bertdotbill-2.9.0.data/data/bin/bill.gui/bert.bill.2f0dc019.css.gz
bertdotbill-2.9.0.data/data/bin/bill.gui/bert.bill.2f0dc019.css.map
bertdotbill-2.9.0.data/data/bin/bill.gui/index.7a0ae899.js
bertdotbill-2.9.0.data/data/bin/bill.gui/index.7a0ae899.js.br
bertdotbill-2.9.0.data/data/bin/bill.gui/index.7a0ae899.js.gz
bertdotbill-2.9.0.data/data/bin/bill.gui/index.7a0ae899.js.map
bertdotbill-2.9.0.data/data/bin/bill.gui/index.html
bertdotbill-2.9.0.data/data/bin/bill.gui/index.html.br
bertdotbill-2.9.0.data/data/bin/bill.gui/index.html.gz
bertdotbill-2.9.0.data/data/bin/bill.gui/logo_api_active.089debfa.png
bertdotbill-2.9.0.data/data/bin/bill.gui/logo_api_inactive.29c5dfcc.png
bertdotbill-2.9.0.data/data/bin/bill.gui/open-sans-v17-latin_cyrillic-italic.fed68991.woff
bertdotbill-2.9.0.dist-info/METADATA
bertdotbill-2.9.0.dist-info/WHEEL
bertdotbill-2.9.0.dist-info/entry_points.txt
bertdotbill-2.9.0.dist-info/top_level.txt
bertdotbill-2.9.0.dist-info/RECORD
